<annotation>
	<folder>JPEGImages</folder>
	<filename>000091.jpg</filename>
	<path>/home/zbr/VOCdevkit/VOC2007/JPEGImages/000091.jpg</path>
	<source>
		<database>Unknown</database>
	</source>
	<size>
		<width>416</width>
		<height>416</height>
		<depth>3</depth>
	</size>
	<segmented>0</segmented>
	<object>
		<name>plastic-garbage</name>
		<pose>Unspecified</pose>
		<truncated>0</truncated>
		<difficult>0</difficult>
		<bndbox>
			<xmin>67</xmin>
			<ymin>207</ymin>
			<xmax>120</xmax>
			<ymax>239</ymax>
		</bndbox>
	</object>
	<object>
		<name>branch</name>
		<pose>Unspecified</pose>
		<truncated>0</truncated>
		<difficult>0</difficult>
		<bndbox>
			<xmin>70</xmin>
			<ymin>130</ymin>
			<xmax>132</xmax>
			<ymax>170</ymax>
		</bndbox>
	</object>
</annotation>
