<annotation>
	<folder>JPEGImages</folder>
	<filename>001830.jpg</filename>
	<path>/home/zbr/VOCdevkit/VOC2007/JPEGImages/001830.jpg</path>
	<source>
		<database>Unknown</database>
	</source>
	<size>
		<width>416</width>
		<height>416</height>
		<depth>3</depth>
	</size>
	<segmented>0</segmented>
	<object>
		<name>bottle</name>
		<pose>Unspecified</pose>
		<truncated>0</truncated>
		<difficult>0</difficult>
		<bndbox>
			<xmin>86</xmin>
			<ymin>102</ymin>
			<xmax>177</xmax>
			<ymax>186</ymax>
		</bndbox>
	</object>
	<object>
		<name>bottle</name>
		<pose>Unspecified</pose>
		<truncated>0</truncated>
		<difficult>0</difficult>
		<bndbox>
			<xmin>198</xmin>
			<ymin>105</ymin>
			<xmax>278</xmax>
			<ymax>250</ymax>
		</bndbox>
	</object>
	<object>
		<name>bottle</name>
		<pose>Unspecified</pose>
		<truncated>0</truncated>
		<difficult>0</difficult>
		<bndbox>
			<xmin>158</xmin>
			<ymin>251</ymin>
			<xmax>205</xmax>
			<ymax>326</ymax>
		</bndbox>
	</object>
	<object>
		<name>plastic-garbage</name>
		<pose>Unspecified</pose>
		<truncated>0</truncated>
		<difficult>0</difficult>
		<bndbox>
			<xmin>279</xmin>
			<ymin>57</ymin>
			<xmax>381</xmax>
			<ymax>204</ymax>
		</bndbox>
	</object>
</annotation>
